pycounts_sf2023/.gitignore
pycounts_sf2023/.readthedocs.yml
pycounts_sf2023/CHANGELOG.md
pycounts_sf2023/CONDUCT.md
pycounts_sf2023/CONTRIBUTING.md
pycounts_sf2023/docs/changelog.md
pycounts_sf2023/docs/conduct.md
pycounts_sf2023/docs/conf.py
pycounts_sf2023/docs/contributing.md
pycounts_sf2023/docs/example.ipynb
pycounts_sf2023/docs/index.md
pycounts_sf2023/docs/make.bat
pycounts_sf2023/docs/Makefile
pycounts_sf2023/docs/requirements.txt
pycounts_sf2023/LICENSE
pycounts_sf2023/poetry.lock
pycounts_sf2023/pyproject.toml
pycounts_sf2023/README.md
pycounts_sf2023/src/pycounts_sf2023/__init__.py
pycounts_sf2023/src/pycounts_sf2023/plotting.py
pycounts_sf2023/src/pycounts_sf2023/pycounts.py
pycounts_sf2023/tests/einstein.txt
pycounts_sf2023/tests/test_pycounts_sf2023.py
pycounts_sf2023/zen.txt
pycounts_sf2023-0.1.0.dist-info/LICENSE
pycounts_sf2023-0.1.0.dist-info/METADATA
pycounts_sf2023-0.1.0.dist-info/WHEEL
pycounts_sf2023-0.1.0.dist-info/RECORD
